tables.libs/libbz2-a273e504.so.1.0.6
tables.libs/libblosc2-c71b5e5e.so.4
tables.libs/libhdf5-6dcce2ca.so.310.3.0
tables/linkextension.cpython-312-x86_64-linux-gnu.so
tables/utilsextension.pyx
tables/tableextension.cpython-312-x86_64-linux-gnu.so
tables/utilsextension.pxd
tables/utils.py
tables/lrucacheextension.cpython-312-x86_64-linux-gnu.so
tables/group.py
tables/file.py
tables/_comp_bzip2.pyx
tables/hdf5extension.cpython-312-x86_64-linux-gnu.so
tables/parameters.py
tables/libblosc2.so
tables/leaf.py
tables/lrucacheextension.pyx
tables/registry.py
tables/tableextension.pyx
tables/hdf5extension.pxd
tables/indexesextension.cpython-312-x86_64-linux-gnu.so
tables/exceptions.py
tables/link.py
tables/description.py
tables/table.py
tables/__init__.py
tables/indexes.py
tables/indexesextension.pyx
tables/expression.py
tables/undoredo.py
tables/atom.py
tables/_comp_bzip2.cpython-312-x86_64-linux-gnu.so
tables/_comp_lzo.pyx
tables/_version.py
tables/_comp_lzo.cpython-312-x86_64-linux-gnu.so
tables/unimplemented.py
tables/definitions.pxd
tables/carray.py
tables/node.py
tables/utilsextension.cpython-312-x86_64-linux-gnu.so
tables/req_versions.py
tables/path.py
tables/lrucacheextension.pxd
tables/filters.py
tables/linkextension.pyx
tables/array.py
tables/conditions.py
tables/attributeset.py
tables/flavor.py
tables/earray.py
tables/vlarray.py
tables/hdf5extension.pyx
tables/idxutils.py
tables/index.py
tables/scripts/pt2to3.py
tables/scripts/ptdump.py
tables/scripts/__init__.py
tables/scripts/ptrepack.py
tables/scripts/pttree.py
tables/nodes/__init__.py
tables/nodes/filenode.py
tables/nodes/tests/test_filenode_v1.h5
tables/nodes/tests/test_filenode.xbm
tables/nodes/tests/__init__.py
tables/nodes/tests/test_filenode.dat
tables/nodes/tests/test_filenode.py
tables/tests/test_timetype.py
tables/tests/test_aux.py
tables/tests/test_direct_chunk.py
tables/tests/test_indexvalues.py
tables-3.10.2.dist-info/top_level.txt
tables-3.10.2.dist-info/RECORD
tables-3.10.2.dist-info/LICENSE.txt
tables-3.10.2.dist-info/entry_points.txt
tables-3.10.2.dist-info/METADATA
tables-3.10.2.dist-info/WHEEL
